pyARB/__init__.py
pyARB/__main__.py
pyARB/exceptions.py
pyARB/localization_generator.py
pyARB/localize.py
pyARB/localization/generated_components.py
pyARB/localization/arbs/en_US.arb
pyARB/localization/arbs/es_ES.arb
pyARB/localization/arbs/pt_BR.arb
pyarb-1.2.0.dist-info/METADATA
pyarb-1.2.0.dist-info/WHEEL
pyarb-1.2.0.dist-info/entry_points.txt
pyarb-1.2.0.dist-info/licenses/LICENSE
pyarb-1.2.0.dist-info/RECORD
