Metadata-Version: 2.1
Name: pyARB
Version: 1.2.0
Summary: A localization library for python utilizing Google's ARB format for Flutter
Project-URL: Homepage, https://github.com/Koratun/pyARB
Project-URL: Bug Tracker, https://github.com/Koratun/pyARB/issues
Author-email: Koratun <danmitch@uat.edu>
License-File: LICENSE
Classifier: License :: OSI Approved :: MIT License
Classifier: Operating System :: OS Independent
Classifier: Programming Language :: Python :: 3
Requires-Python: >=3.8
